setup.py
apsis/__init__.py
apsis.egg-info/PKG-INFO
apsis.egg-info/SOURCES.txt
apsis.egg-info/dependency_links.txt
apsis.egg-info/requires.txt
apsis.egg-info/top_level.txt
apsis/assistants/__init__.py
apsis/assistants/experiment_assistant.py
apsis/assistants/lab_assistant.py
apsis/config/logging.conf
apsis/demos/__init__.py
apsis/demos/demo_MNIST.py
apsis/demos/demo_MNIST_MCMC.py
apsis/demos/demo_MNIST_NN.py
apsis/demos/demo_branin.py
apsis/demos/demo_noise.py
apsis/models/__init__.py
apsis/models/candidate.py
apsis/models/experiment.py
apsis/models/parameter_definition.py
apsis/optimizers/__init__.py
apsis/optimizers/bayesian_optimization.py
apsis/optimizers/optimizer.py
apsis/optimizers/random_search.py
apsis/optimizers/bayesian/__init__.py
apsis/optimizers/bayesian/acquisition_functions.py
apsis/utilities/__init__.py
apsis/utilities/benchmark_functions.py
apsis/utilities/file_utils.py
apsis/utilities/import_utils.py
apsis/utilities/logging_utils.py
apsis/utilities/optimizer_utils.py
apsis/utilities/plot_utils.py
apsis/utilities/randomization.py