Metadata-Version: 1.1
Name: apsis
Version: 0.1.1
Summary: Toolkit for hyperparameter optimization for machine learning algorithms.
Home-page: https://github.com/FrederikDiehl/apsis
Author: Frederik Diehl, Andreas Jauch
Author-email: apsis-users@googlegroups.com
License: MIT
Keywords: bayesian optimization machine learning
Platform: UNKNOWN
Classifier: Development Status :: 4 - Beta
Classifier: Intended Audience :: Science/Research
Classifier: Topic :: Software Development :: Build Tools
Classifier: License :: OSI Approved :: MIT License
Classifier: Programming Language :: Python :: 2.7
